nacos_tools/__init__.py
nacos_tools/core.py
nacos_tools/config/__init__.py
nacos_tools/config/manager.py
nacos_tools/config/nacos.py
nacos_tools/config/tools.py
nacos_tools/discovery/__init__.py
nacos_tools/discovery/manager.py
nacos_tools/discovery/nacos.py
nacos_tools/lib/__init__.py
nacos_tools/lib/helper.py
nacos_tools/tools/__init__.py
nacos_tools/tools/manager.py
nacos_tools/tools/cache/__init__.py
nacos_tools/tools/cache/base.py
nacos_tools/tools/cache/impl/__init__.py
nacos_tools/tools/cache/impl/redis.py
nacos_tools/tools/storage/__init__.py
nacos_tools/tools/storage/base.py
nacos_tools/tools/storage/impl/__init__.py
nacos_tools/tools/storage/impl/aliyun_oss.py
nacos_tools/tools/vdb/__init__.py
nacos_tools/tools/vdb/base.py
nacos_tools/tools/vdb/connectors/__init__.py
nacos_tools/tools/vdb/connectors/mysql.py
nacos_tools/tools/vdb/connectors/postgres.py
nacos_tools-0.1.11.dist-info/METADATA
nacos_tools-0.1.11.dist-info/WHEEL
nacos_tools-0.1.11.dist-info/top_level.txt
nacos_tools-0.1.11.dist-info/RECORD
