Metadata-Version: 2.2
Name: nacos-tools
Version: 0.1.11
Summary: A Python library for Nacos integration with virtual database (async/sync), cache, and storage systems
Home-page: https://github.com/oscarou1992/nacos_tools
Author: Oscar Ou
Author-email: oscar.ou@tamaredge.ai
Classifier: Programming Language :: Python :: 3
Classifier: License :: OSI Approved :: MIT License
Classifier: Operating System :: OS Independent
Requires-Python: >=3.6
Requires-Dist: sqlalchemy>=1.4.0
Requires-Dist: pymysql>=1.1.1
Requires-Dist: psycopg2-binary>=2.9.5
Requires-Dist: aiomysql>=0.2.0
Requires-Dist: asyncpg>=0.27.0
Requires-Dist: redis>=4.0.0
Requires-Dist: nacos-sdk-python>=2.0.7
Requires-Dist: oss2>=2.17.0
Dynamic: author
Dynamic: author-email
Dynamic: classifier
Dynamic: description
Dynamic: description-content-type
Dynamic: home-page
Dynamic: requires-dist
Dynamic: requires-python
Dynamic: summary
